skywalking/__init__.py
skywalking/agent/__init__.py
skywalking/agent/protocol/__init__.py
skywalking/agent/protocol/grpc.py
skywalking/agent/protocol/grpc_aio.py
skywalking/agent/protocol/http.py
skywalking/agent/protocol/http_aio.py
skywalking/agent/protocol/interceptors.py
skywalking/agent/protocol/interceptors_aio.py
skywalking/agent/protocol/kafka.py
skywalking/agent/protocol/kafka_aio.py
skywalking/bootstrap/__init__.py
skywalking/bootstrap/cli/__init__.py
skywalking/bootstrap/cli/sw_python.py
skywalking/bootstrap/cli/utility/__init__.py
skywalking/bootstrap/cli/utility/runner.py
skywalking/bootstrap/hooks/__init__.py
skywalking/bootstrap/hooks/uwsgi_hook.py
skywalking/bootstrap/loader/__init__.py
skywalking/bootstrap/loader/sitecustomize.py
skywalking/client/__init__.py
skywalking/client/grpc.py
skywalking/client/grpc_aio.py
skywalking/client/http.py
skywalking/client/http_aio.py
skywalking/client/kafka.py
skywalking/client/kafka_aio.py
skywalking/command/__init__.py
skywalking/command/base_command.py
skywalking/command/command_service.py
skywalking/command/executors/__init__.py
skywalking/command/executors/command_executor.py
skywalking/command/executors/noop_command_executor.py
skywalking/command/executors/profile_task_command_executor.py
skywalking/command/profile_task_command.py
skywalking/config.py
skywalking/decorators.py
skywalking/log/__init__.py
skywalking/log/formatter.py
skywalking/log/sw_logging.py
skywalking/loggings.py
skywalking/meter/__init__.py
skywalking/meter/counter.py
skywalking/meter/gauge.py
skywalking/meter/histogram.py
skywalking/meter/meter.py
skywalking/meter/meter_service.py
skywalking/meter/pvm/__init__.py
skywalking/meter/pvm/cpu_usage.py
skywalking/meter/pvm/data_source.py
skywalking/meter/pvm/gc_data.py
skywalking/meter/pvm/mem_usage.py
skywalking/meter/pvm/thread_data.py
skywalking/plugins/__init__.py
skywalking/plugins/sw_aiohttp.py
skywalking/plugins/sw_aioredis.py
skywalking/plugins/sw_aiormq.py
apache_skywalking-1.2.0.dist-info/LICENSE
apache_skywalking-1.2.0.dist-info/METADATA
apache_skywalking-1.2.0.dist-info/WHEEL
apache_skywalking-1.2.0.dist-info/entry_points.txt
apache_skywalking-1.2.0.dist-info/RECORD
