Metadata-Version: 2.1
Name: apache-skywalking
Version: 1.2.0
Summary: The Python Agent for Apache SkyWalking, which provides the native tracing/metrics/logging/profiling abilities for Python projects.
Home-page: https://skywalking.apache.org/
License: Apache-2.0
Keywords: skywalking,tracing,metrics,logging,profiling,observability,distributed-tracing,apm,python
Author: Apache Software Foundation
Author-email: dev@skywalking.apache.org
Maintainer: Apache SkyWalking Community
Maintainer-email: dev@skywalking.apache.org
Requires-Python: >=3.8,<=3.13
Classifier: License :: OSI Approved :: Apache Software License
Classifier: Operating System :: OS Independent
Classifier: Programming Language :: Python
Classifier: Programming Language :: Python :: 3
Classifier: Programming Language :: Python :: 3.8
Classifier: Programming Language :: Python :: 3.9
Classifier: Programming Language :: Python :: 3.10
Classifier: Programming Language :: Python :: 3.11
Classifier: Topic :: Software Development
Classifier: Topic :: System :: Monitoring
Provides-Extra: all
Provides-Extra: async
Provides-Extra: asynchttp
Provides-Extra: asynckafka
Provides-Extra: http
Provides-Extra: kafka
Provides-Extra: sync
Requires-Dist: aiohttp (>=3.7.4,<4.0.0) ; extra == "all" or extra == "async" or extra == "asynchttp"
Requires-Dist: aiokafka (>=0.8.0,<0.9.0) ; extra == "all" or extra == "async" or extra == "asynckafka"
Requires-Dist: grpcio
Requires-Dist: grpcio-tools
Requires-Dist: kafka-python ; extra == "all" or extra == "sync" or extra == "kafka"
Requires-Dist: packaging
Requires-Dist: psutil (<=5.9.5)
Requires-Dist: requests (>=2.26.0) ; extra == "all" or extra == "sync" or extra == "http"
Requires-Dist: uvloop (>=0.17.0,<0.18.0) ; extra == "all" or extra == "async" or extra == "asynchttp" or extra == "asynckafka"
Requires-Dist: wrapt
Project-URL: Bug Tracker, https://github.com/apache/skywalking/issues
Project-URL: Documentation, https://skywalking.apache.org/docs/skywalking-python/next/readme/
Project-URL: Repository, https://github.com/apache/skywalking-python
